dlffmpeg.py
dlffmpeg-0.6.3.data/scripts/dlffmpeg
dlffmpeg-0.6.3.dist-info/DESCRIPTION.rst
dlffmpeg-0.6.3.dist-info/METADATA
dlffmpeg-0.6.3.dist-info/RECORD
dlffmpeg-0.6.3.dist-info/WHEEL
dlffmpeg-0.6.3.dist-info/metadata.json
dlffmpeg-0.6.3.dist-info/top_level.txt
